prettierplot/__init__.py
prettierplot/cat.py
prettierplot/data.py
prettierplot/eval.py
prettierplot/facet.py
prettierplot/line.py
prettierplot/num.py
prettierplot/plotter.py
prettierplot/style.py
prettierplot/util.py
prettierplot/datasets/__init__.py
prettierplot/datasets/attrition/__init__.py
prettierplot/datasets/attrition/data.pkl
prettierplot/datasets/housing/__init__.py
prettierplot/datasets/housing/test.pkl
prettierplot/datasets/housing/train.pkl
prettierplot/datasets/titanic/__init__.py
prettierplot/datasets/titanic/test.pkl
prettierplot/datasets/titanic/train.pkl
prettierplot-0.1.2.dist-info/LICENSE
prettierplot-0.1.2.dist-info/METADATA
prettierplot-0.1.2.dist-info/WHEEL
prettierplot-0.1.2.dist-info/top_level.txt
prettierplot-0.1.2.dist-info/RECORD
