Metadata-Version: 2.1
Name: prettierplot
Version: 0.1.2
Summary: Quickly create prettier plots
Home-page: https://github.com/petersontylerd/prettierplot
Maintainer: Tyler Peterson
Maintainer-email: petersontylerd@gmail.com
License: MIT
Project-URL: bug tracker, https://github.com/petersontylerd/prettierplot/issues
Project-URL: source code, https://github.com/petersontylerd/prettierplot
Keywords: machine learning,data science
Platform: UNKNOWN
Classifier: Development Status :: 3 - Alpha
Classifier: Intended Audience :: Developers
Classifier: Intended Audience :: Science/Research
Classifier: Topic :: Scientific/Engineering
Classifier: Topic :: Scientific/Engineering :: Information Analysis
Classifier: Topic :: Scientific/Engineering :: Visualization
Classifier: Topic :: Software Development
Classifier: Topic :: Software Development :: Libraries :: Python Modules
Classifier: License :: OSI Approved :: MIT License
Classifier: Programming Language :: Python :: 3
Classifier: Operating System :: OS Independent
Requires-Python: >=3.6.1
Requires-Dist: matplotlib (>=3.2.1)
Requires-Dist: numpy (>=1.18.2)
Requires-Dist: pandas (>=1.0.3)
Requires-Dist: seaborn (>=0.10.0)
Requires-Dist: scikit-learn (>=0.22.2.post1)
Requires-Dist: scipy (>=1.4.1)
Requires-Dist: squarify (>=0.4.3)
